{"name":"flux-framework","className":"DataModel","filePaths":["default.project.json"],"children":[{"name":"ReplicatedStorage","className":"ReplicatedStorage","children":[{"name":"client","className":"Script","filePaths":["src/client/init.client.luau"]},{"name":"lab","className":"ModuleScript","filePaths":["lab/init.luau"],"children":[{"name":"flags","className":"ModuleScript","filePaths":["lab/flags.luau"]},{"name":"results","className":"ModuleScript","filePaths":["lab/results.luau"]},{"name":"types","className":"ModuleScript","filePaths":["lab/types.luau"]},{"name":"suite","className":"ModuleScript","filePaths":["lab/suite.luau"]}]},{"name":"shared","className":"Folder","children":[{"name":"do_cleaning","className":"ModuleScript","filePaths":["src/shared/do_cleaning.luau"]},{"name":"flux","className":"ModuleScript","filePaths":["src/shared/flux/init.luau"],"children":[{"name":"computed","className":"ModuleScript","filePaths":["src/shared/flux/computed.luau"]},{"name":"effect","className":"ModuleScript","filePaths":["src/shared/flux/effect.luau"]},{"name":"element","className":"ModuleScript","filePaths":["src/shared/flux/element.luau"]},{"name":"graph","className":"ModuleScript","filePaths":["src/shared/flux/graph.luau"]},{"name":"hydrate","className":"ModuleScript","filePaths":["src/shared/flux/hydrate.luau"]},{"name":"node","className":"ModuleScript","filePaths":["src/shared/flux/node.luau"]},{"name":"scopes","className":"ModuleScript","filePaths":["src/shared/flux/scopes.luau"]},{"name":"source","className":"ModuleScript","filePaths":["src/shared/flux/source.luau"]},{"name":"spring","className":"ModuleScript","filePaths":["src/shared/flux/spring.luau"]},{"name":"types","className":"ModuleScript","filePaths":["src/shared/flux/types.luau"]},{"name":"context","className":"ModuleScript","filePaths":["src/shared/flux/context.luau"]}]},{"name":"queue","className":"ModuleScript","filePaths":["src/shared/queue.luau"]},{"name":"spring","className":"ModuleScript","filePaths":["src/shared/spring.luau"]},{"name":"stack","className":"ModuleScript","filePaths":["src/shared/stack.luau"]}]},{"name":"tests","className":"Folder","children":[{"name":"adts","className":"Folder","children":[{"name":"queue","className":"ModuleScript","filePaths":["tests/adts/queue.luau"]},{"name":"stack","className":"ModuleScript","filePaths":["tests/adts/stack.luau"]}]},{"name":"flux","className":"Folder","children":[{"name":"computed","className":"ModuleScript","filePaths":["tests/flux/computed.luau"]},{"name":"effect","className":"ModuleScript","filePaths":["tests/flux/effect.luau"]},{"name":"instances","className":"ModuleScript","filePaths":["tests/flux/instances.luau"]},{"name":"is_node","className":"ModuleScript","filePaths":["tests/flux/is_node.luau"]},{"name":"node_gc","className":"ModuleScript","filePaths":["tests/flux/node_gc.luau"]},{"name":"source","className":"ModuleScript","filePaths":["tests/flux/source.luau"]},{"name":"context","className":"ModuleScript","filePaths":["tests/flux/context.luau"]}]},{"name":"lab","className":"Folder","children":[{"name":"utilities","className":"ModuleScript","filePaths":["tests/lab/utilities.luau"]}]},{"name":"spring","className":"ModuleScript","filePaths":["tests/spring.luau"]}]}]},{"name":"ServerScriptService","className":"ServerScriptService","children":[{"name":"server","className":"Folder","children":[{"name":"lab_plugin","className":"Script","filePaths":["src/server/lab_plugin/init.meta.json","src/server/lab_plugin/init.server.luau"]},{"name":"server","className":"Script","filePaths":["src/server/server.server.luau"]}]}]},{"name":"SoundService","className":"SoundService"},{"name":"Workspace","className":"Workspace"}]}